{
  "channelId": "UC3lLPAOb4cKzj6UN71cqeyQ",
  "generatedAt": "2026-03-09T19:54:08.145Z",
  "videos": [
    {
      "id": "InQp3Vo5wxE",
      "title": "UEP! COM ANAM? [742] - VINYA A ST. MARIA, LA COVA DE SON OLIVER A CAMPOS I GALTES DE PORC NEGRE.",
      "description": "Aquesta setmana, l’amo de Can Uep!, en Toni Ballador anirà fins a Santa Maria del camí per ajudar a un petit celler amb les feines de poda. I mentre feim les feines, conversarem sobre els seus inicis i com veuen el futur a aquesta professió. Llavors amb l’ajuda d’un tractor arrabassarem les arrels d’una antiga plantació de vinyes i preparar la terra per sembrar-ne de bell nou. Acabarem les feines berenant i tastant un bon vi de la casa. El mestre de mestres, en Felip Munar visitarà la finca de Son Oliver de Campos on hi ha una cova on antigament si extreia marès per construir edificis, la Seu de Palma entre molts d'altres, i llavors fou una fàbrica on es cultivaven xampinyons. Podrem parlar amb antics treballadors que després de molts d’anys es retrobaran allà i ens contaran la seva experiència en aquells temps, serà molt emocionant. Al rebost d’aquesta setmana, un jove de Ciutat amb una trajectòria important en el món de la gastronomia, ens cuinarà unes galtes de porc negre amb un estil una mica modern. A la vall de Sóller, coneixerem a una veïna que té un petit hort amb molts de tarongers. La veurem collint taronges i amb l’ajuda de les seves gallines adobarà amb fems els arbres. També ens mostrarà un fruit exòtic paraescut a la llimona i que té un sabor molt fort. \n\n\"Uep! Com anam?\" és un programa de televisió d'IB3.\n\nhttp://ib3.org/uepcomanam\nhttp://facebook.com/uepcomanam",
      "thumbnail": "https://i.ytimg.com/vi/InQp3Vo5wxE/maxresdefault.jpg",
      "channelId": "UC3lLPAOb4cKzj6UN71cqeyQ",
      "channelTitle": "Uep! Com anam? IB3",
      "publishedAt": "2026-01-30T10:49:45Z",
      "categories": [
        "mitjans"
      ],
      "sourceChannelId": "UC3lLPAOb4cKzj6UN71cqeyQ",
      "duration": "PT1H10M30S",
      "durationSeconds": 4230,
      "isShort": false,
      "viewCount": 466,
      "likeCount": 11,
      "commentCount": 0,
      "defaultAudioLanguage": "ca",
      "defaultLanguage": "ca",
      "tags": [
        "uep",
        "ib3",
        "tv",
        "illes balears",
        "mallorca",
        "pages",
        "rural",
        "camp",
        "eivissa",
        "formentera",
        "menorca",
        "animals",
        "vaca",
        "porc",
        "conill",
        "ovella",
        "xot",
        "pollet",
        "gallina",
        "gall"
      ]
    },
    {
      "id": "fcgBYKT__ww",
      "title": "Escola Sa Llavor de Binissalem - Uep IB3",
      "description": "Coneixerem als alumnes de l’escola Sa Llavor de Binissalem, que fan el descans del patí a un petit hort on aprenen a sembrar, a fer feines de camp i aprofitant els beneficis d’estar en contacte amb la natura.\n\n\"Uep! Com anam?\" és un programa de televisió d'IB3.\n\nhttp://ib3.org/uepcomanam\nhttp://facebook.com/uepcomanam",
      "thumbnail": "https://i.ytimg.com/vi/fcgBYKT__ww/maxresdefault.jpg",
      "channelId": "UC3lLPAOb4cKzj6UN71cqeyQ",
      "channelTitle": "Uep! Com anam? IB3",
      "publishedAt": "2026-01-23T08:00:59Z",
      "categories": [
        "mitjans"
      ],
      "sourceChannelId": "UC3lLPAOb4cKzj6UN71cqeyQ",
      "duration": "PT8M12S",
      "durationSeconds": 492,
      "isShort": false,
      "viewCount": 59,
      "likeCount": 2,
      "commentCount": 0,
      "defaultAudioLanguage": "ca",
      "defaultLanguage": "ca",
      "tags": [
        "uep",
        "ib3",
        "tv",
        "illes balears",
        "mallorca",
        "pages",
        "rural",
        "camp",
        "eivissa",
        "formentera",
        "menorca",
        "animals",
        "vaca",
        "porc",
        "conill",
        "ovella",
        "xot",
        "pollet",
        "gallina",
        "gall"
      ]
    },
    {
      "id": "ikJkZ0n7AnI",
      "title": "Greixera d'ous i 50è aniversari de la Coral de Felanitx - Uep IB3",
      "description": "Al rebost d’aquesta setmana, una madona de Felanitx, ens cuinarà una deliciosa greixera d’ous, i després anirem a assajar amb la Coral de Felanitx que l’any passat va celebrar el seu 50è aniversari.   \n\n\"Uep! Com anam?\" és un programa de televisió d'IB3.\n\nhttp://ib3.org/uepcomanam\nhttp://facebook.com/uepcomanam",
      "thumbnail": "https://i.ytimg.com/vi/ikJkZ0n7AnI/maxresdefault.jpg",
      "channelId": "UC3lLPAOb4cKzj6UN71cqeyQ",
      "channelTitle": "Uep! Com anam? IB3",
      "publishedAt": "2026-01-23T08:00:58Z",
      "categories": [
        "mitjans"
      ],
      "sourceChannelId": "UC3lLPAOb4cKzj6UN71cqeyQ",
      "duration": "PT9M25S",
      "durationSeconds": 565,
      "isShort": false,
      "viewCount": 143,
      "likeCount": 6,
      "commentCount": 1,
      "defaultAudioLanguage": "ca",
      "defaultLanguage": "ca",
      "tags": [
        "uep",
        "ib3",
        "tv",
        "illes balears",
        "mallorca",
        "pages",
        "rural",
        "camp",
        "eivissa",
        "formentera",
        "menorca",
        "animals",
        "vaca",
        "porc",
        "conill",
        "ovella",
        "xot",
        "pollet",
        "gallina",
        "gall"
      ]
    },
    {
      "id": "m6IyhCCGh2o",
      "title": "UEP! COM ANAM? [741] - EMPELTS A MONTUÏRI, OLIVAR DE SÓLLER I GREIXERA D’OUS A FELANITX",
      "description": "Aquesta setmana, l’amo de Can Uep!, en Toni Ballador anirà fins a Montuïri per a empeltar un ametller de pruna de frare roig. Veurem tots els arbres que ha empeltat a la seva finca amb un 100% d’efectivitat. També l’ajudarem a sembrar alls paus i com mana la tradició que diu que s’han de sembrar el dia de la conversió de Sant Pau i recollir el dia de Sant Joan abans que surti el sol. El nostre jove youtuber, en Miquel Montoro farà una visita a un jove pagès que va deixar la seva afició per la fotografia per dedicar-se a l’agricultura. El veurem passant el tractor a un olivar de Sóller per triturar restes de poda i a cremar el brancam. També mourem d’olivar una petita guarda d’ovelles i tallarem branques i tanyades per donar-los. Al rebost d’aquesta setmana, una madona de Felanitx, ens cuinarà una deliciosa greixera d’ous, i després anirem a assajar amb la Coral de Felanitx que l’any passat va celebrar el seu 50è aniversari. I també coneixerem als alumnes de l’escola Sa Llavor de Binissalem, que fan el descans del patí a un petit hort on aprenen a sembrar, a fer feines de camp i aprofitant els beneficis d’estar en contacte amb la natura. I com cada setmana, farem gloses i dites amb el nostre mestre de mestres, en Felip Munar i Munar.\n\n\"Uep! Com anam?\" és un programa de televisió d'IB3.\n\nhttp://ib3.org/uepcomanam\nhttp://facebook.com/uepcomanam",
      "thumbnail": "https://i.ytimg.com/vi/m6IyhCCGh2o/maxresdefault.jpg",
      "channelId": "UC3lLPAOb4cKzj6UN71cqeyQ",
      "channelTitle": "Uep! Com anam? IB3",
      "publishedAt": "2026-01-23T08:00:58Z",
      "categories": [
        "mitjans"
      ],
      "sourceChannelId": "UC3lLPAOb4cKzj6UN71cqeyQ",
      "duration": "PT1H4M32S",
      "durationSeconds": 3872,
      "isShort": false,
      "viewCount": 472,
      "likeCount": 10,
      "commentCount": 0,
      "defaultAudioLanguage": "ca",
      "defaultLanguage": "ca",
      "tags": [
        "uep",
        "ib3",
        "tv",
        "illes balears",
        "mallorca",
        "pages",
        "rural",
        "camp",
        "eivissa",
        "formentera",
        "menorca",
        "animals",
        "vaca",
        "porc",
        "conill",
        "ovella",
        "xot",
        "pollet",
        "gallina",
        "gall"
      ]
    },
    {
      "id": "1s5w54bFjlc",
      "title": "Arròs de matances i cosir budells i camaiots - Uep IB3",
      "description": "Al rebost d’aquesta setmana, a Capdepera, coneixem a una parella que fa més de cinquanta anys que estan junts. La dona ens prepararà un arròs de matances al foc i mentre espera que es faci veurem com cusen els budells que després s’empren per omplir de sobrassada. \n\n\"Uep! Com anam?\" és un programa de televisió d'IB3.\n\nhttp://ib3.org/uepcomanam\nhttp://facebook.com/uepcomanam",
      "thumbnail": "https://i.ytimg.com/vi/1s5w54bFjlc/maxresdefault.jpg",
      "channelId": "UC3lLPAOb4cKzj6UN71cqeyQ",
      "channelTitle": "Uep! Com anam? IB3",
      "publishedAt": "2026-01-16T10:09:21Z",
      "categories": [
        "mitjans"
      ],
      "sourceChannelId": "UC3lLPAOb4cKzj6UN71cqeyQ",
      "duration": "PT15M55S",
      "durationSeconds": 955,
      "isShort": false,
      "viewCount": 339,
      "likeCount": 6,
      "commentCount": 1,
      "defaultAudioLanguage": "ca",
      "defaultLanguage": "ca",
      "tags": [
        "uep",
        "ib3",
        "tv",
        "illes balears",
        "mallorca",
        "pages",
        "rural",
        "camp",
        "eivissa",
        "formentera",
        "menorca",
        "animals",
        "vaca",
        "porc",
        "conill",
        "ovella",
        "xot",
        "pollet",
        "gallina",
        "gall"
      ]
    },
    {
      "id": "UTZY4a_9m4w",
      "title": "Entrenament d'un ca de bestiar a can Miquel Adrover des Cau de Felanitx - Uep IB3",
      "description": "A Felanitx, veurem com fan feina amb un ca de bestiar amb una guarda d'ovelles i prepararem una bandada d'oques per anar a les beneïdes de Muro. \n\n\"Uep! Com anam?\" és un programa de televisió d'IB3.\n\nhttp://ib3.org/uepcomanam\nhttp://facebook.com/uepcomanam",
      "thumbnail": "https://i.ytimg.com/vi/UTZY4a_9m4w/maxresdefault.jpg",
      "channelId": "UC3lLPAOb4cKzj6UN71cqeyQ",
      "channelTitle": "Uep! Com anam? IB3",
      "publishedAt": "2026-01-16T10:05:59Z",
      "categories": [
        "mitjans"
      ],
      "sourceChannelId": "UC3lLPAOb4cKzj6UN71cqeyQ",
      "duration": "PT10M36S",
      "durationSeconds": 636,
      "isShort": false,
      "viewCount": 157,
      "likeCount": 2,
      "commentCount": 0,
      "defaultAudioLanguage": "ca",
      "defaultLanguage": "ca",
      "tags": [
        "uep",
        "ib3",
        "tv",
        "illes balears",
        "mallorca",
        "pages",
        "rural",
        "camp",
        "eivissa",
        "formentera",
        "menorca",
        "animals",
        "vaca",
        "porc",
        "conill",
        "ovella",
        "xot",
        "pollet",
        "gallina",
        "gall"
      ]
    },
    {
      "id": "iRWbhmtaieo",
      "title": "UEP! COM ANAM? [740] - FOGUERONS, TORRADES, XIMBOMBADES I EL TERNAL DEL PI PER SANT ANTONI.",
      "description": "Aquesta setmana, l’amo de Can Uep!, en Toni Ballador, serà a Alcúdia per conèixer a un pagès, glossador i ximbomber. Donarem menjar a les ovelles, exsecallarem arbres fruitals i farem un cremadís, amb el caliu torrarem i acabarem cantant una cançó amb la ximbomba amb motiu de Sant Antoni.\nEl nostre mestre de mestres, en Felip Munar i Munar, des de Pollença, ens redescobrirà un ofici del qual tan sols queda un artesà en tota l’illa que s’hi dedica. Veurem quin és el procés per fer les graneres i com s’aprofiten les restes per donar-los una segona vida. I per acabar coneixerem de ben a prop el ternal i el pagès que s'encarrega del seu funcionament, peces fonamentals en la celebració de Sant Antoni a Pollença. A Felanitx, veurem com fan feina amb un ca de bestiar amb una guarda d'ovelles i prepararem una bandada d'oques per anar a les beneïdes de Muro. Al rebost d’aquesta setmana, a Capdepera, coneixem a una parella que fa més de cinquanta anys que estan junts. La dona ens prepararà un arròs de matances al foc i mentre espera que es faci veurem com cusen els budells que després s’empren per omplir de sobrassada. \n\n\"Uep! Com anam?\" és un programa de televisió d'IB3.\n\nhttp://ib3.org/uepcomanam\nhttp://facebook.com/uepcomanam",
      "thumbnail": "https://i.ytimg.com/vi/iRWbhmtaieo/maxresdefault.jpg",
      "channelId": "UC3lLPAOb4cKzj6UN71cqeyQ",
      "channelTitle": "Uep! Com anam? IB3",
      "publishedAt": "2026-01-16T10:04:09Z",
      "categories": [
        "mitjans"
      ],
      "sourceChannelId": "UC3lLPAOb4cKzj6UN71cqeyQ",
      "duration": "PT1H9M37S",
      "durationSeconds": 4177,
      "isShort": false,
      "viewCount": 394,
      "likeCount": 13,
      "commentCount": 0,
      "defaultAudioLanguage": "ca",
      "defaultLanguage": "ca",
      "tags": [
        "uep",
        "ib3",
        "tv",
        "illes balears",
        "mallorca",
        "pages",
        "rural",
        "camp",
        "eivissa",
        "formentera",
        "menorca",
        "animals",
        "vaca",
        "porc",
        "conill",
        "ovella",
        "xot",
        "pollet",
        "gallina",
        "gall"
      ]
    },
    {
      "id": "oNoYBojDt4g",
      "title": "Finca musicalitzada a Eivissa - Uep IB3",
      "description": "A Eivissa, visitarem l'única finca ecològica musicalitzada de tota Espanya. Veurem en què consisteix aquest projecte, sembrarem fonoll i collirem advocats per després reposar la botiga.\n\n\"Uep! Com anam?\" és un programa de televisió d'IB3.\n\nhttp://ib3.org/uepcomanam\nhttp://facebook.com/uepcomanam",
      "thumbnail": "https://i.ytimg.com/vi/oNoYBojDt4g/maxresdefault.jpg",
      "channelId": "UC3lLPAOb4cKzj6UN71cqeyQ",
      "channelTitle": "Uep! Com anam? IB3",
      "publishedAt": "2026-01-09T08:01:10Z",
      "categories": [
        "mitjans"
      ],
      "sourceChannelId": "UC3lLPAOb4cKzj6UN71cqeyQ",
      "duration": "PT9M19S",
      "durationSeconds": 559,
      "isShort": false,
      "viewCount": 114,
      "likeCount": 2,
      "commentCount": 0,
      "defaultAudioLanguage": "ca",
      "defaultLanguage": "ca",
      "tags": [
        "uep",
        "ib3",
        "tv",
        "illes balears",
        "mallorca",
        "pages",
        "rural",
        "camp",
        "eivissa",
        "formentera",
        "menorca",
        "animals",
        "vaca",
        "porc",
        "conill",
        "ovella",
        "xot",
        "pollet",
        "gallina",
        "gall"
      ]
    },
    {
      "id": "fjd1sVENULo",
      "title": "UEP! COM ANAM? [739] - CÍTRICS A PALMA, PORCS NEGRES, FINCA MUSICALITZADA I ROTLLETS VIETNAMITES",
      "description": "Aquesta setmana, l’amo de Can Uep!, en Toni Ballador, serà a Palma on collirem llimones i taronges a una finca amb més de quatre mil arbres. Collirem oliva mentre coneixem els inicis d’aquesta finca i d’aquest gran projecte que han fet possible fins a tres generacions. I per acabar la jornada berenarem tots en companyia. El nostre jove pagès, en Lander, se’n va fins a Son Serra de Marina. Començarem donant menjar a unes quantes truges de porc negre i veurem els habitatges on es resguarden. Ens prepararem i ajudarem la manescala a vacunar les truges i veurem com es fa una ecografia en aquests animals. I per acabar, com calia esperar, tastarem una sobrassada de porc negre. A Eivissa, visitarem l'única finca ecològica musicalitzada de tota Espanya. Veurem en què consisteix aquest projecte, sembrarem fonoll i collirem advocats per després reposar la botiga.\nAl rebost d’aquesta setmana, una jove que crea contingut sobre una vida saludable a les xarxes socials, ens preparà dues versions de “rotllets vietnamites” però amb producte local i ben encertades per deixar de costat el torró de Nadal. I com cada setmana, farem gloses i dites amb el nostre mestre de mestres, en Felip Munar i Munar.\n\n\"Uep! Com anam?\" és un programa de televisió d'IB3.\n\nhttp://ib3.org/uepcomanam\nhttp://facebook.com/uepcomanam",
      "thumbnail": "https://i.ytimg.com/vi/fjd1sVENULo/maxresdefault.jpg",
      "channelId": "UC3lLPAOb4cKzj6UN71cqeyQ",
      "channelTitle": "Uep! Com anam? IB3",
      "publishedAt": "2026-01-09T08:00:55Z",
      "categories": [
        "mitjans"
      ],
      "sourceChannelId": "UC3lLPAOb4cKzj6UN71cqeyQ",
      "duration": "PT1H17M43S",
      "durationSeconds": 4663,
      "isShort": false,
      "viewCount": 548,
      "likeCount": 14,
      "commentCount": 0,
      "defaultAudioLanguage": "ca",
      "defaultLanguage": "ca",
      "tags": [
        "uep",
        "ib3",
        "tv",
        "illes balears",
        "mallorca",
        "pages",
        "rural",
        "camp",
        "eivissa",
        "formentera",
        "menorca",
        "animals",
        "vaca",
        "porc",
        "conill",
        "ovella",
        "xot",
        "pollet",
        "gallina",
        "gall"
      ]
    },
    {
      "id": "K_o3yYe36Q0",
      "title": "Rotllets vietnamites amb producte local - Uep IB3",
      "description": "Al rebost d’aquesta setmana, una jove que crea contingut sobre una vida saludable a les xarxes socials, ens preparà dues versions de “rotllets vietnamites” però amb producte local i ben encertades per deixar de costat el torró de Nadal.\n\n\"Uep! Com anam?\" és un programa de televisió d'IB3.\n\nhttp://ib3.org/uepcomanam\nhttp://facebook.com/uepcomanam",
      "thumbnail": "https://i.ytimg.com/vi/K_o3yYe36Q0/maxresdefault.jpg",
      "channelId": "UC3lLPAOb4cKzj6UN71cqeyQ",
      "channelTitle": "Uep! Com anam? IB3",
      "publishedAt": "2026-01-09T08:00:34Z",
      "categories": [
        "mitjans"
      ],
      "sourceChannelId": "UC3lLPAOb4cKzj6UN71cqeyQ",
      "duration": "PT11M2S",
      "durationSeconds": 662,
      "isShort": false,
      "viewCount": 112,
      "likeCount": 1,
      "commentCount": 0,
      "defaultAudioLanguage": "ca",
      "defaultLanguage": "ca",
      "tags": [
        "uep",
        "ib3",
        "tv",
        "illes balears",
        "mallorca",
        "pages",
        "rural",
        "camp",
        "eivissa",
        "formentera",
        "menorca",
        "animals",
        "vaca",
        "porc",
        "conill",
        "ovella",
        "xot",
        "pollet",
        "gallina",
        "gall"
      ]
    },
    {
      "id": "CdpiFx3iEFE",
      "title": "Mel de Ses Tanques de Can Serra de Sóller - Uep IB3",
      "description": "A Sóller, treure’m la mel de Ses Tanques de Can Serra amb un apicultor aficionat. Veurem quin és el procés d’extracció d’aquesta delícia i ens faran saber alguns consells i altres precaucions que haurem de seguir per fer-ho de la millor manera.\n\n\"Uep! Com anam?\" és un programa de televisió d'IB3.\n\nhttp://ib3.org/uepcomanam\nhttp://facebook.com/uepcomanam",
      "thumbnail": "https://i.ytimg.com/vi/CdpiFx3iEFE/maxresdefault.jpg",
      "channelId": "UC3lLPAOb4cKzj6UN71cqeyQ",
      "channelTitle": "Uep! Com anam? IB3",
      "publishedAt": "2026-01-02T08:00:31Z",
      "categories": [
        "mitjans"
      ],
      "sourceChannelId": "UC3lLPAOb4cKzj6UN71cqeyQ",
      "duration": "PT16M55S",
      "durationSeconds": 1015,
      "isShort": false,
      "viewCount": 102,
      "likeCount": 0,
      "commentCount": 0,
      "defaultAudioLanguage": "ca",
      "defaultLanguage": "ca",
      "tags": [
        "uep",
        "ib3",
        "tv",
        "illes balears",
        "mallorca",
        "pages",
        "rural",
        "camp",
        "eivissa",
        "formentera",
        "menorca",
        "animals",
        "vaca",
        "porc",
        "conill",
        "ovella",
        "xot",
        "pollet",
        "gallina",
        "gall"
      ]
    },
    {
      "id": "HkbDScqDKGo",
      "title": "UEP! COM ANAM? [738] - VAQUES A GALATZÓ, ARBRES FRUITERS A EIVISSA I CANELONS D’ANY NOU A MARRATXÍ",
      "description": "Aquesta setmana, l’amo de Can Uep!, en Toni Ballador, serà a Calvià. Ajudarem un pagès a pujar una vacada dins un remolc triant les que durem a la finca del Galatzó i les que no, una de les tantes accions que duen a terme des de l’associació per al manteniment d’aquesta finca i que anirem coneixent arreu del programa. El nostre jove pagès, en Lander, visitarà una finca a Eivissa per ajudar una família d’agricultors ecològics a sembrar pruneres i albercoquers. Coneixerem l’associació a qui pertanyen i quins són els objectius d’aquesta. I acabarem la jornada collint col kale per després poder oferir als clients. A Sóller, treure’m la mel de Ses Tanques de Can Serra amb un apicultor aficionat. Veurem quin és el procés d’extracció d’aquesta delícia i ens faran saber alguns consells i altres precaucions que haurem de seguir per fer-ho de la millor manera. Al rebost d’aquesta setmana, serem al Museu del Fang a Marratxí, on un jove i la seva padrina ens prepararan un plat ben típic d’aquestes dates com són els canelons d’any nou. I com cada setmana, farem gloses i dites amb el nostre mestre de mestres, en Felip Munar i Munar.\n\n\"Uep! Com anam?\" és un programa de televisió d'IB3.\n\nhttp://ib3.org/uepcomanam\nhttp://facebook.com/uepcomanam",
      "thumbnail": "https://i.ytimg.com/vi/HkbDScqDKGo/maxresdefault.jpg",
      "channelId": "UC3lLPAOb4cKzj6UN71cqeyQ",
      "channelTitle": "Uep! Com anam? IB3",
      "publishedAt": "2026-01-02T08:00:18Z",
      "categories": [
        "mitjans"
      ],
      "sourceChannelId": "UC3lLPAOb4cKzj6UN71cqeyQ",
      "duration": "PT1H10M49S",
      "durationSeconds": 4249,
      "isShort": false,
      "viewCount": 459,
      "likeCount": 8,
      "commentCount": 0,
      "defaultAudioLanguage": "ca",
      "defaultLanguage": "ca",
      "tags": [
        "uep",
        "ib3",
        "tv",
        "illes balears",
        "mallorca",
        "pages",
        "rural",
        "camp",
        "eivissa",
        "formentera",
        "menorca",
        "animals",
        "vaca",
        "porc",
        "conill",
        "ovella",
        "xot",
        "pollet",
        "gallina",
        "gall"
      ]
    },
    {
      "id": "68pplszPdQs",
      "title": "Canelons d'any nou a Marratxí - Uep IB3",
      "description": "Al rebost d’aquesta setmana, serem al Museu del Fang a Marratxí, on un net i la seva padrina ens prepararan un plat ben típic d’aquestes dates com són els canelons d’any nou.\n\n\"Uep! Com anam?\" és un programa de televisió d'IB3.\n\nhttp://ib3.org/uepcomanam\nhttp://facebook.com/uepcomanam",
      "thumbnail": "https://i.ytimg.com/vi/68pplszPdQs/maxresdefault.jpg",
      "channelId": "UC3lLPAOb4cKzj6UN71cqeyQ",
      "channelTitle": "Uep! Com anam? IB3",
      "publishedAt": "2026-01-02T08:00:07Z",
      "categories": [
        "mitjans"
      ],
      "sourceChannelId": "UC3lLPAOb4cKzj6UN71cqeyQ",
      "duration": "PT12M19S",
      "durationSeconds": 739,
      "isShort": false,
      "viewCount": 241,
      "likeCount": 9,
      "commentCount": 1,
      "defaultAudioLanguage": "ca",
      "defaultLanguage": "ca",
      "tags": [
        "uep",
        "ib3",
        "tv",
        "illes balears",
        "mallorca",
        "pages",
        "rural",
        "camp",
        "eivissa",
        "formentera",
        "menorca",
        "animals",
        "vaca",
        "porc",
        "conill",
        "ovella",
        "xot",
        "pollet",
        "gallina",
        "gall"
      ]
    },
    {
      "id": "_WeAjtB-10k",
      "title": "Polvorons de blat xeixa a Porreres - Uep IB3",
      "description": "Al rebost d’aquesta setmana, extreure’m farina del blat de xeixa amb un molí de pedra que després utilitzarem per fer un dels dolços més típics i estimats d’aquestes dates com són els polvorons.\n\n\"Uep! Com anam?\" és un programa de televisió d'IB3.\n\nhttp://ib3.org/uepcomanam\nhttp://facebook.com/uepcomanam",
      "thumbnail": "https://i.ytimg.com/vi/_WeAjtB-10k/maxresdefault.jpg",
      "channelId": "UC3lLPAOb4cKzj6UN71cqeyQ",
      "channelTitle": "Uep! Com anam? IB3",
      "publishedAt": "2025-12-26T08:00:51Z",
      "categories": [
        "mitjans"
      ],
      "sourceChannelId": "UC3lLPAOb4cKzj6UN71cqeyQ",
      "duration": "PT8M23S",
      "durationSeconds": 503,
      "isShort": false,
      "viewCount": 120,
      "likeCount": 5,
      "commentCount": 0,
      "defaultAudioLanguage": "ca",
      "defaultLanguage": "ca",
      "tags": [
        "uep",
        "ib3",
        "tv",
        "illes balears",
        "mallorca",
        "pages",
        "rural",
        "camp",
        "eivissa",
        "formentera",
        "menorca",
        "animals",
        "vaca",
        "porc",
        "conill",
        "ovella",
        "xot",
        "pollet",
        "gallina",
        "gall"
      ]
    },
    {
      "id": "ISd8s8iRTrQ",
      "title": "UEP! COM ANAM? [737] - SEMBRAR COLS A FORMENTERA, PARE I FILL DE CAMPOS, BLAT DE XEIXA I POLVORONS.",
      "description": "Aquesta setmana, l’amo de Can Uep!, en Toni Ballador, serà a Formentera per visitar a un antic conegut.  Ajudarem el nostre amfitrió a sembrar algunes cols i a netejar l’hort d’algunes males herbes. Reviurem antigues vivències i veurem diverses rèpliques d’eines tradicionals. El nostre jove pagès, en Lander, passarà una jornada el camp amb un pare i el seu fill a Campos. Segarem herba fresca per donar menjar a les cabres i veurem com el pare ha construït eines a la mida del seu fill que després utilitza a la finca per ajudar al seu pare. I acabarem estellant uns quants troncs per escalfar-nos ara que ve el fred.A una finca de Son Mesquida, a Felanitx, sembrarem deu quarterades de blat de xeixa amb un enginyer agrònom. Qui ens farà saber els inicis de la sembra d’aquest tipus de blat. Al rebost d’aquesta setmana, extreure’m farina del blat de xeixa amb un molí de pedra que després utilitzarem per fer un dels dolços més típics i estimats d’aquestes dates com són els polvorons. I com cada setmana, farem gloses i dites amb el nostre mestre de mestres, en Felip Munar i Munar.\n\n\"Uep! Com anam?\" és un programa de televisió d'IB3.\n\nhttp://ib3.org/uepcomanam\nhttp://facebook.com/uepcomanam",
      "thumbnail": "https://i.ytimg.com/vi/ISd8s8iRTrQ/maxresdefault.jpg",
      "channelId": "UC3lLPAOb4cKzj6UN71cqeyQ",
      "channelTitle": "Uep! Com anam? IB3",
      "publishedAt": "2025-12-26T08:00:22Z",
      "categories": [
        "mitjans"
      ],
      "sourceChannelId": "UC3lLPAOb4cKzj6UN71cqeyQ",
      "duration": "PT1H1M59S",
      "durationSeconds": 3719,
      "isShort": false,
      "viewCount": 411,
      "likeCount": 5,
      "commentCount": 0,
      "defaultAudioLanguage": "ca",
      "defaultLanguage": "ca",
      "tags": [
        "uep",
        "ib3",
        "tv",
        "illes balears",
        "mallorca",
        "pages",
        "rural",
        "camp",
        "eivissa",
        "formentera",
        "menorca",
        "animals",
        "vaca",
        "porc",
        "conill",
        "ovella",
        "xot",
        "pollet",
        "gallina",
        "gall"
      ]
    },
    {
      "id": "C2gpxpqs-uI",
      "title": "Sembram blat xeixa Son Mesquida  - Uep IB3",
      "description": "A una finca de Son Mesquida, a Felanitx, sembrarem deu quarterades de blat de xeixa amb un enginyer agrònom. Qui ens farà saber els inicis de la sembra d’aquest tipus de blat.\n\n\"Uep! Com anam?\" és un programa de televisió d'IB3.\n\nhttp://ib3.org/uepcomanam\nhttp://facebook.com/uepcomanam",
      "thumbnail": "https://i.ytimg.com/vi/C2gpxpqs-uI/maxresdefault.jpg",
      "channelId": "UC3lLPAOb4cKzj6UN71cqeyQ",
      "channelTitle": "Uep! Com anam? IB3",
      "publishedAt": "2025-12-26T08:00:16Z",
      "categories": [
        "mitjans"
      ],
      "sourceChannelId": "UC3lLPAOb4cKzj6UN71cqeyQ",
      "duration": "PT5M13S",
      "durationSeconds": 313,
      "isShort": false,
      "viewCount": 89,
      "likeCount": 2,
      "commentCount": 0,
      "defaultAudioLanguage": "ca",
      "defaultLanguage": "ca",
      "tags": [
        "uep",
        "ib3",
        "tv",
        "illes balears",
        "mallorca",
        "pages",
        "rural",
        "camp",
        "eivissa",
        "formentera",
        "menorca",
        "animals",
        "vaca",
        "porc",
        "conill",
        "ovella",
        "xot",
        "pollet",
        "gallina",
        "gall"
      ]
    },
    {
      "id": "4VFaBu5NQyM",
      "title": "Torró de peix de pasta reial.- Uep IB3",
      "description": "Al rebost d’aquesta setmana, un xef privat de la zona de Palma, ens ensenyarà el procés a seguir per preparar torró de peix de pasta reial.\n\n\"Uep! Com anam?\" és un programa de televisió d'IB3.\n\nhttp://ib3.org/uepcomanam\nhttp://facebook.com/uepcomanam",
      "thumbnail": "https://i.ytimg.com/vi/4VFaBu5NQyM/maxresdefault.jpg",
      "channelId": "UC3lLPAOb4cKzj6UN71cqeyQ",
      "channelTitle": "Uep! Com anam? IB3",
      "publishedAt": "2025-12-22T14:41:06Z",
      "categories": [
        "mitjans"
      ],
      "sourceChannelId": "UC3lLPAOb4cKzj6UN71cqeyQ",
      "duration": "PT8M45S",
      "durationSeconds": 525,
      "isShort": false,
      "viewCount": 79,
      "likeCount": 2,
      "commentCount": 1,
      "defaultAudioLanguage": "ca",
      "defaultLanguage": "ca",
      "tags": [
        "uep",
        "ib3",
        "tv",
        "illes balears",
        "mallorca",
        "pages",
        "rural",
        "camp",
        "eivissa",
        "formentera",
        "menorca",
        "animals",
        "vaca",
        "porc",
        "conill",
        "ovella",
        "xot",
        "pollet",
        "gallina",
        "gall"
      ]
    },
    {
      "id": "e_QV0ka-NdE",
      "title": "Porcelleta menorquina per a Nadal - Uep IB3",
      "description": "A Menorca, visitarem l’explotació porcina del major productor de porcella de l’illa. Veurem en què consisteix una jornada de feina dins aquest sector, al mateix temps que coneixem les diferències entre el porc negre i el blanc a més d’altres curiositats d’aquests animals.\n\n\"Uep! Com anam?\" és un programa de televisió d'IB3.\n\nhttp://ib3.org/uepcomanam\nhttp://facebook.com/uepcomanam",
      "thumbnail": "https://i.ytimg.com/vi/e_QV0ka-NdE/maxresdefault.jpg",
      "channelId": "UC3lLPAOb4cKzj6UN71cqeyQ",
      "channelTitle": "Uep! Com anam? IB3",
      "publishedAt": "2025-12-22T14:37:57Z",
      "categories": [
        "mitjans"
      ],
      "sourceChannelId": "UC3lLPAOb4cKzj6UN71cqeyQ",
      "duration": "PT7M55S",
      "durationSeconds": 475,
      "isShort": false,
      "viewCount": 174,
      "likeCount": 3,
      "commentCount": 0,
      "defaultAudioLanguage": "ca",
      "defaultLanguage": "ca",
      "tags": [
        "uep",
        "ib3",
        "tv",
        "illes balears",
        "mallorca",
        "pages",
        "rural",
        "camp",
        "eivissa",
        "formentera",
        "menorca",
        "animals",
        "vaca",
        "porc",
        "conill",
        "ovella",
        "xot",
        "pollet",
        "gallina",
        "gall"
      ]
    },
    {
      "id": "Fyo0Ol2ZyD4",
      "title": "UEP! COM ANAM? [736] - ABELLES DE LLUBÍ, FAREM LLENYA, PORCELLES MENORQUINES I TORRÓ DE PASTA REIAL",
      "description": "Aquesta setmana, l’amo de Can Uep!, en Toni Ballador, visitarà la finca d’un perruquer jubilat aficionat a l’apicultura a Llubí. Després de collir unes quantes clementines, veurem de primera mà com és la feina d’un apicultor i quin és el procés a seguir fins que s’extreu la mel de les bresques de l’abella. I com era d'esperar, acabarem tastant aquesta mel acabada d’extreure.\nEl nostre jove pagès, en Lander, serà a Marratxí per conèixer a dos germans que fan feina junts al camp. Començarem arrabassant uns quants ametllers morts a causa de la Xilel·la i donarem menjar a unes quantes ovelles abans de posar-nos mans a la feina. I després d’haver tallat els troncs amb una motoserra, passarem a fer-ne estelles per a la seva posterior venda.\nA Menorca, visitarem l’explotació porcina del major productor de porcella de l’illa. Veurem en què consisteix una jornada de feina dins aquest sector, al mateix temps que coneixem les diferències entre el porc negre i el blanc a més d’altres curiositats d’aquests animals. Al rebost d’aquesta setmana, un xef privat de la zona de Palma, ens ensenyarà el procés a seguir per preparar torró de peix de pasta reial. I com cada setmana, farem gloses i dites amb el nostre mestre de mestres, en Felip Munar i Munar.\n\n\"Uep! Com anam?\" és un programa de televisió d'IB3.\n\nhttp://ib3.org/uepcomanam\nhttp://facebook.com/uepcomanam",
      "thumbnail": "https://i.ytimg.com/vi/Fyo0Ol2ZyD4/maxresdefault.jpg",
      "channelId": "UC3lLPAOb4cKzj6UN71cqeyQ",
      "channelTitle": "Uep! Com anam? IB3",
      "publishedAt": "2025-12-22T14:34:20Z",
      "categories": [
        "mitjans"
      ],
      "sourceChannelId": "UC3lLPAOb4cKzj6UN71cqeyQ",
      "duration": "PT1H3M36S",
      "durationSeconds": 3816,
      "isShort": false,
      "viewCount": 350,
      "likeCount": 3,
      "commentCount": 0,
      "defaultAudioLanguage": "ca",
      "defaultLanguage": "ca",
      "tags": [
        "uep",
        "ib3",
        "tv",
        "illes balears",
        "mallorca",
        "pages",
        "rural",
        "camp",
        "eivissa",
        "formentera",
        "menorca",
        "animals",
        "vaca",
        "porc",
        "conill",
        "ovella",
        "xot",
        "pollet",
        "gallina",
        "gall"
      ]
    },
    {
      "id": "_-pSTpMeyhI",
      "title": "UEP! COM ANAM? [735] - PARADES EN CRESTALL, FORMATGERIA A CIUTADELLA I PANADES DE CARAGOLS",
      "description": "Aquesta setmana, l’amo de Can Uep!, en Toni Ballador, serà a Lloseta per ajudar un pagès a tornar a posar en marxa el seu hort. Sembrarem cebes tendres i colfloris i un amic del nostre amfitrió ens ensenyarà un nou compost natural fet a partir de carbó. Acabem asseguts a taula berenant i coneixent un poc més als nostres protagonistes. El nostre jove pagès, en Lander, visitarà la finca de Sant Joan Gran de Ciutadella, per conèixer a un jove ramader i la seva família. Donarem menjar a les vaques i llet als vedells abans d’amollar-les a pasturar. Untarem formatges amb oli per dur-los assecar i acabem parlant dels seus orígens i de la vida com a pagès.\nA Inca, amb un jove pagès, collirem clementines i ens donarà a conèixer consells per a la seva producció, les diferències entre clementines i taronges i com diferenciar les de suc i les que són per menjar. A Felanitx, visitarem una granja dedicada a la cria i reproducció del caragol bover i amb la mare i les filles elaborarem la recepta d’aquesta setmana, panades de caragols.\nI com cada setmana, farem gloses i dites amb el nostre mestre de mestres, en Felip Munar i Munar.\n\n\"Uep! Com anam?\" és un programa de televisió d'IB3.\n\nhttp://ib3.org/uepcomanam\nhttp://facebook.com/uepcomanam",
      "thumbnail": "https://i.ytimg.com/vi/_-pSTpMeyhI/maxresdefault.jpg",
      "channelId": "UC3lLPAOb4cKzj6UN71cqeyQ",
      "channelTitle": "Uep! Com anam? IB3",
      "publishedAt": "2025-12-12T08:01:00Z",
      "categories": [
        "mitjans"
      ],
      "sourceChannelId": "UC3lLPAOb4cKzj6UN71cqeyQ",
      "duration": "PT1H12M15S",
      "durationSeconds": 4335,
      "isShort": false,
      "viewCount": 585,
      "likeCount": 10,
      "commentCount": 0,
      "defaultAudioLanguage": "ca",
      "defaultLanguage": "ca",
      "tags": [
        "uep",
        "ib3",
        "tv",
        "illes balears",
        "mallorca",
        "pages",
        "rural",
        "camp",
        "eivissa",
        "formentera",
        "menorca",
        "animals",
        "vaca",
        "porc",
        "conill",
        "ovella",
        "xot",
        "pollet",
        "gallina",
        "gall"
      ]
    },
    {
      "id": "9hRJvOF1kAg",
      "title": "Taronges i clementines per Nadal a Inca - Uep IB3",
      "description": "A Inca, amb un jove pagès, collirem clementines i ens donarà a conèixer consells per a la seva producció, les diferències entre clementines i taronges i com diferenciar les de suc i les que són per menjar.\n\n\"Uep! Com anam?\" és un programa de televisió d'IB3.\n\nhttp://ib3.org/uepcomanam\nhttp://facebook.com/uepcomanam",
      "thumbnail": "https://i.ytimg.com/vi/9hRJvOF1kAg/maxresdefault.jpg",
      "channelId": "UC3lLPAOb4cKzj6UN71cqeyQ",
      "channelTitle": "Uep! Com anam? IB3",
      "publishedAt": "2025-12-12T08:00:20Z",
      "categories": [
        "mitjans"
      ],
      "sourceChannelId": "UC3lLPAOb4cKzj6UN71cqeyQ",
      "duration": "PT7M21S",
      "durationSeconds": 441,
      "isShort": false,
      "viewCount": 59,
      "likeCount": 3,
      "commentCount": 0,
      "defaultAudioLanguage": "ca",
      "defaultLanguage": "ca",
      "tags": [
        "uep",
        "ib3",
        "tv",
        "illes balears",
        "mallorca",
        "pages",
        "rural",
        "camp",
        "eivissa",
        "formentera",
        "menorca",
        "animals",
        "vaca",
        "porc",
        "conill",
        "ovella",
        "xot",
        "pollet",
        "gallina",
        "gall"
      ]
    },
    {
      "id": "IgQoSoYtHIU",
      "title": "Granja i panades de caragols a Son Mesquida - Uep IB3",
      "description": "A Felanitx, visitarem una granja dedicada a la cria i reproducció del caragol bover i amb la mare i les filles elaborarem la recepta d’aquesta setmana, panades de caragols.\n\n\"Uep! Com anam?\" és un programa de televisió d'IB3.\n\nhttp://ib3.org/uepcomanam\nhttp://facebook.com/uepcomanam",
      "thumbnail": "https://i.ytimg.com/vi/IgQoSoYtHIU/maxresdefault.jpg",
      "channelId": "UC3lLPAOb4cKzj6UN71cqeyQ",
      "channelTitle": "Uep! Com anam? IB3",
      "publishedAt": "2025-12-12T08:00:20Z",
      "categories": [
        "mitjans"
      ],
      "sourceChannelId": "UC3lLPAOb4cKzj6UN71cqeyQ",
      "duration": "PT17M36S",
      "durationSeconds": 1056,
      "isShort": false,
      "viewCount": 179,
      "likeCount": 3,
      "commentCount": 0,
      "defaultAudioLanguage": "ca",
      "defaultLanguage": "ca",
      "tags": [
        "uep",
        "ib3",
        "tv",
        "illes balears",
        "mallorca",
        "pages",
        "rural",
        "camp",
        "eivissa",
        "formentera",
        "menorca",
        "animals",
        "vaca",
        "porc",
        "conill",
        "ovella",
        "xot",
        "pollet",
        "gallina",
        "gall"
      ]
    },
    {
      "id": "xao8IUeh9tY",
      "title": "Tamborets mariandos fets pel padrí i la neta Maria de la Salut- Uep IB3",
      "description": "A la finca d’Es Pujolet a Maria de la salut veurem com un padrí ensenya a la seva neta a fer un tamboret de fusta, després de collir un parell de magranes i moraduix del seu petit hort.\n\n\"Uep! Com anam?\" és un programa de televisió d'IB3.\n\nhttp://ib3.org/uepcomanam\nhttp://facebook.com/uepcomanam",
      "thumbnail": "https://i.ytimg.com/vi/xao8IUeh9tY/maxresdefault.jpg",
      "channelId": "UC3lLPAOb4cKzj6UN71cqeyQ",
      "channelTitle": "Uep! Com anam? IB3",
      "publishedAt": "2025-12-05T08:01:24Z",
      "categories": [
        "mitjans"
      ],
      "sourceChannelId": "UC3lLPAOb4cKzj6UN71cqeyQ",
      "duration": "PT9M47S",
      "durationSeconds": 587,
      "isShort": false,
      "viewCount": 122,
      "likeCount": 3,
      "commentCount": 0,
      "defaultAudioLanguage": "ca",
      "defaultLanguage": "ca",
      "tags": [
        "uep",
        "ib3",
        "tv",
        "illes balears",
        "mallorca",
        "pages",
        "rural",
        "camp",
        "eivissa",
        "formentera",
        "menorca",
        "animals",
        "vaca",
        "porc",
        "conill",
        "ovella",
        "xot",
        "pollet",
        "gallina",
        "gall"
      ]
    },
    {
      "id": "eCeMu0yLJ4k",
      "title": "Arròs melós de rellom de porc ibèric a Algaida  - Uep IB3",
      "description": "Al rebost d’aquesta setmana, una jove al·lota d’Algaida ens cuinarà un meravellós arròs melós de rellom ibèric, serà boníssim!\n\n\"Uep! Com anam?\" és un programa de televisió d'IB3.\n\nhttp://ib3.org/uepcomanam\nhttp://facebook.com/uepcomanam",
      "thumbnail": "https://i.ytimg.com/vi/eCeMu0yLJ4k/maxresdefault.jpg",
      "channelId": "UC3lLPAOb4cKzj6UN71cqeyQ",
      "channelTitle": "Uep! Com anam? IB3",
      "publishedAt": "2025-12-05T08:00:56Z",
      "categories": [
        "mitjans"
      ],
      "sourceChannelId": "UC3lLPAOb4cKzj6UN71cqeyQ",
      "duration": "PT10M14S",
      "durationSeconds": 614,
      "isShort": false,
      "viewCount": 123,
      "likeCount": 7,
      "commentCount": 0,
      "defaultAudioLanguage": "ca",
      "defaultLanguage": "ca",
      "tags": [
        "uep",
        "ib3",
        "tv",
        "illes balears",
        "mallorca",
        "pages",
        "rural",
        "camp",
        "eivissa",
        "formentera",
        "menorca",
        "animals",
        "vaca",
        "porc",
        "conill",
        "ovella",
        "xot",
        "pollet",
        "gallina",
        "gall"
      ]
    },
    {
      "id": "VdE_bhOzQL8",
      "title": "UEP! COM ANAM? [734] - PITAIA A SANT LLUÍS, OLIVAR DE SÓLLER, TAMBORETS MARIANDOS I ARRÒS MELÓS.",
      "description": "Aquesta setmana, l’amo de Can Uep!, en Toni Ballador, farà una visita a un veïnat de Sant Lluís. Primer l’ajudarem a donar menjar a les ànneres i llavors ens mostrarà la gran plantació de pitaies on ens ensenyarà com fer empelts de diverses castes i quines propietats té aquesta fruita del dragó.\nEl nostre jove pagès, en Lander, anirà a donar una mà als operaris d’una empresa de jardineria i poda amb les feines a un gran olivar de Sóller. Veurem com preparen les eines i com treballa de bon de veres una trituradora que fan servir per eliminar troncs i restes de poda.\nA la finca d’Es Pujolet a Maria de la salut veurem com un padrí ensenya a la seva neta a fer un tamboret de fusta, després de collir un parell de magranes i moraduix del seu petit hort. Al rebost d’aquesta setmana, una jove al·lota d’Algaida ens cuinarà un meravellós arròs melós de rellom ibèric, serà boníssim! I com cada setmana, farem gloses i dites amb el nostre mestre de mestres, en Felip Munar i Munar.\n\n\"Uep! Com anam?\" és un programa de televisió d'IB3.\n\nhttp://ib3.org/uepcomanam\nhttp://facebook.com/uepcomanam",
      "thumbnail": "https://i.ytimg.com/vi/VdE_bhOzQL8/maxresdefault.jpg",
      "channelId": "UC3lLPAOb4cKzj6UN71cqeyQ",
      "channelTitle": "Uep! Com anam? IB3",
      "publishedAt": "2025-12-05T08:00:44Z",
      "categories": [
        "mitjans"
      ],
      "sourceChannelId": "UC3lLPAOb4cKzj6UN71cqeyQ",
      "duration": "PT1H8M34S",
      "durationSeconds": 4114,
      "isShort": false,
      "viewCount": 771,
      "likeCount": 12,
      "commentCount": 1,
      "defaultAudioLanguage": "ca",
      "defaultLanguage": "ca",
      "tags": [
        "uep",
        "ib3",
        "tv",
        "illes balears",
        "mallorca",
        "pages",
        "rural",
        "camp",
        "eivissa",
        "formentera",
        "menorca",
        "animals",
        "vaca",
        "porc",
        "conill",
        "ovella",
        "xot",
        "pollet",
        "gallina",
        "gall"
      ]
    },
    {
      "id": "w1ypwxD891c",
      "title": "UEP! COM ANAM? [733] - PAGÈS DE 94 ANYS, OLI TREUER D'ALGAIDA I CARABASSA AMB BOLETS A SÓLLER",
      "description": "Aquesta setmana, l’amo de Can Uep!, en Toni Ballador, anirà a Petra per conèixer a un pagès de 94 anys. Començarem agafant forces amb un bon berenar i després posarem a punt una antiga sembradora, amb la qual sembrarem favó i acabarem descobrint a un ajudant ben curiós que segur ens deixarà sorpresos. El nostre jove pagès, en Lander, visitarà la finca Treuer d'Algaida. Veurem de primera mà tot el procés, des de collir olives amb vibradors fins al triatge i premsat d’aquestes. I acabarem fent un tast d’aliments maridats amb aquest oli tan especial. A Santa Maria del Camí posarem llana a fruiters joves, agafarem un carabassí enfilat i farem solcs per sembrar-hi moraduix. Al rebost d’aquesta setmana, a Sóller veurem com es prepara un plat ben tradicional i de temporada, carabassa ofegada amb bolets. I com cada setmana, farem gloses i dites amb el nostre mestre de mestres, en Felip Munar i Munar.\n\n\"Uep! Com anam?\" és un programa de televisió d'IB3.\n\nhttp://ib3.org/uepcomanam\nhttp://facebook.com/uepcomanam",
      "thumbnail": "https://i.ytimg.com/vi/w1ypwxD891c/maxresdefault.jpg",
      "channelId": "UC3lLPAOb4cKzj6UN71cqeyQ",
      "channelTitle": "Uep! Com anam? IB3",
      "publishedAt": "2025-11-28T08:01:23Z",
      "categories": [
        "mitjans"
      ],
      "sourceChannelId": "UC3lLPAOb4cKzj6UN71cqeyQ",
      "duration": "PT1H13M9S",
      "durationSeconds": 4389,
      "isShort": false,
      "viewCount": 644,
      "likeCount": 11,
      "commentCount": 0,
      "defaultAudioLanguage": "ca",
      "defaultLanguage": "ca",
      "tags": [
        "uep",
        "ib3",
        "tv",
        "illes balears",
        "mallorca",
        "pages",
        "rural",
        "camp",
        "eivissa",
        "formentera",
        "menorca",
        "animals",
        "vaca",
        "porc",
        "conill",
        "ovella",
        "xot",
        "pollet",
        "gallina",
        "gall"
      ]
    },
    {
      "id": "jGWsso6C7DU",
      "title": "Llana per protegir els arbres joves a Santa Maria del Camí - Uep IB3",
      "description": "A Santa Maria del Camí posarem llana a fruiters joves, agafarem un carabassí enfilat i farem solcs per sembrar-hi moraduix.\n\n\"Uep! Com anam?\" és un programa de televisió d'IB3.\n\nhttp://ib3.org/uepcomanam\nhttp://facebook.com/uepcomanam",
      "thumbnail": "https://i.ytimg.com/vi/jGWsso6C7DU/maxresdefault.jpg",
      "channelId": "UC3lLPAOb4cKzj6UN71cqeyQ",
      "channelTitle": "Uep! Com anam? IB3",
      "publishedAt": "2025-11-28T08:01:06Z",
      "categories": [
        "mitjans"
      ],
      "sourceChannelId": "UC3lLPAOb4cKzj6UN71cqeyQ",
      "duration": "PT10M25S",
      "durationSeconds": 625,
      "isShort": false,
      "viewCount": 113,
      "likeCount": 3,
      "commentCount": 0,
      "defaultAudioLanguage": "ca",
      "defaultLanguage": "ca",
      "tags": [
        "uep",
        "ib3",
        "tv",
        "illes balears",
        "mallorca",
        "pages",
        "rural",
        "camp",
        "eivissa",
        "formentera",
        "menorca",
        "animals",
        "vaca",
        "porc",
        "conill",
        "ovella",
        "xot",
        "pollet",
        "gallina",
        "gall"
      ]
    },
    {
      "id": "aj_3EXpCfkU",
      "title": "Carabassa ofegada amb bolets a Can Boqueta de Sóller  - Uep IB3",
      "description": "Al rebost d’aquesta setmana, a Sóller veurem com es prepara un plat ben tradicional i de temporada, carabassa ofegada amb bolets.\n\n\"Uep! Com anam?\" és un programa de televisió d'IB3.\n\nhttp://ib3.org/uepcomanam\nhttp://facebook.com/uepcomanam",
      "thumbnail": "https://i.ytimg.com/vi/aj_3EXpCfkU/maxresdefault.jpg",
      "channelId": "UC3lLPAOb4cKzj6UN71cqeyQ",
      "channelTitle": "Uep! Com anam? IB3",
      "publishedAt": "2025-11-28T08:00:04Z",
      "categories": [
        "mitjans"
      ],
      "sourceChannelId": "UC3lLPAOb4cKzj6UN71cqeyQ",
      "duration": "PT12M47S",
      "durationSeconds": 767,
      "isShort": false,
      "viewCount": 103,
      "likeCount": 4,
      "commentCount": 0,
      "defaultAudioLanguage": "ca",
      "defaultLanguage": "ca",
      "tags": [
        "uep",
        "ib3",
        "tv",
        "illes balears",
        "mallorca",
        "pages",
        "rural",
        "camp",
        "eivissa",
        "formentera",
        "menorca",
        "animals",
        "vaca",
        "porc",
        "conill",
        "ovella",
        "xot",
        "pollet",
        "gallina",
        "gall"
      ]
    },
    {
      "id": "D6vdE-8sFt8",
      "title": "UEP! COM ANAM? [732]  - OLIVES EN FAMÍLIA, INNOVACIÓ A UNA VAQUERIA I FRIT DE PORC A BINIARAIX",
      "description": "Aquesta setmana, amb l’amo de Can Uep!, en Toni Ballador, compartirem una jornada ben familiar dins el camp a Porto Cristo. Tomarem i collirem olives a una finca amb més de setanta oliveres, i menjarem bunyols fets per la madona. La ximbomba de l’amo en Toni i una xeremia, posaran la banda sonora d’un matí ben arrelat a la tradició. El nostre jove pagès, en Lander, serà a Llubí per visitar una de les poques vaqueries que queden a Mallorca. Descobrirem com s’han adaptat als nous temps, incorporant innovació i tecnologia a les feines més tradicionals per continuar formant part del sector ramader. A Sant Josep de sa Talaia, visitarem a un pagès i ramader membre de la Cooperativa Ramadera d’Eivissa i coneixerem el conjunt d’animals que té. Al rebost d’aquesta setmana, cuinarem un frit de porc o de matances a un lloc amb molta història les rentadores públiques de Biniaraix. \nI com cada setmana, farem gloses i dites amb el nostre mestre de mestres, en Felip Munar i Munar.\n\n\"Uep! Com anam?\" és un programa de televisió d'IB3.\n\nhttp://ib3.org/uepcomanam\nhttp://facebook.com/uepcomanam",
      "thumbnail": "https://i.ytimg.com/vi/D6vdE-8sFt8/maxresdefault.jpg",
      "channelId": "UC3lLPAOb4cKzj6UN71cqeyQ",
      "channelTitle": "Uep! Com anam? IB3",
      "publishedAt": "2025-11-21T16:28:09Z",
      "categories": [
        "mitjans"
      ],
      "sourceChannelId": "UC3lLPAOb4cKzj6UN71cqeyQ",
      "duration": "PT1H14M35S",
      "durationSeconds": 4475,
      "isShort": false,
      "viewCount": 878,
      "likeCount": 12,
      "commentCount": 0,
      "defaultAudioLanguage": "ca",
      "defaultLanguage": "ca",
      "tags": [
        "uep",
        "ib3",
        "tv",
        "illes balears",
        "mallorca",
        "pages",
        "rural",
        "camp",
        "eivissa",
        "formentera",
        "menorca",
        "animals",
        "vaca",
        "porc",
        "conill",
        "ovella",
        "xot",
        "pollet",
        "gallina",
        "gall"
      ]
    },
    {
      "id": "KsU7btUPkv0",
      "title": "Frit de porc a les rentadores de Biniaraix - Uep IB3",
      "description": "Al rebost d’aquesta setmana, cuinarem un frit de porc o de matances a un lloc amb molta història les rentadores públiques de Biniaraix\n\n\"Uep! Com anam?\" és un programa de televisió d'IB3.\n\nhttp://ib3.org/uepcomanam\nhttp://facebook.com/uepcomanam",
      "thumbnail": "https://i.ytimg.com/vi/KsU7btUPkv0/maxresdefault.jpg",
      "channelId": "UC3lLPAOb4cKzj6UN71cqeyQ",
      "channelTitle": "Uep! Com anam? IB3",
      "publishedAt": "2025-11-21T08:00:33Z",
      "categories": [
        "mitjans"
      ],
      "sourceChannelId": "UC3lLPAOb4cKzj6UN71cqeyQ",
      "duration": "PT10M29S",
      "durationSeconds": 629,
      "isShort": false,
      "viewCount": 301,
      "likeCount": 13,
      "commentCount": 0,
      "defaultAudioLanguage": "ca",
      "defaultLanguage": "ca",
      "tags": [
        "uep",
        "ib3",
        "tv",
        "illes balears",
        "mallorca",
        "pages",
        "rural",
        "camp",
        "eivissa",
        "formentera",
        "menorca",
        "animals",
        "vaca",
        "porc",
        "conill",
        "ovella",
        "xot",
        "pollet",
        "gallina",
        "gall"
      ]
    },
    {
      "id": "J9Fb0d7bIgY",
      "title": "Ovelles i menets a Sant Josep de sa Talaia - Uep IB3",
      "description": "A Sant Josep de sa Talaia, visitarem a un pagès i ramader membre de la Cooperativa Ramadera d’Eivissa i coneixerem el conjunt d’animals que té.\n\n\"Uep! Com anam?\" és un programa de televisió d'IB3.\n\nhttp://ib3.org/uepcomanam\nhttp://facebook.com/uepcomanam",
      "thumbnail": "https://i.ytimg.com/vi/J9Fb0d7bIgY/maxresdefault.jpg",
      "channelId": "UC3lLPAOb4cKzj6UN71cqeyQ",
      "channelTitle": "Uep! Com anam? IB3",
      "publishedAt": "2025-11-21T08:00:32Z",
      "categories": [
        "mitjans"
      ],
      "sourceChannelId": "UC3lLPAOb4cKzj6UN71cqeyQ",
      "duration": "PT7M43S",
      "durationSeconds": 463,
      "isShort": false,
      "viewCount": 208,
      "likeCount": 5,
      "commentCount": 0,
      "defaultAudioLanguage": "ca",
      "defaultLanguage": "ca",
      "tags": [
        "uep",
        "ib3",
        "tv",
        "illes balears",
        "mallorca",
        "pages",
        "rural",
        "camp",
        "eivissa",
        "formentera",
        "menorca",
        "animals",
        "vaca",
        "porc",
        "conill",
        "ovella",
        "xot",
        "pollet",
        "gallina",
        "gall"
      ]
    },
    {
      "id": "T7kh8gaoXxE",
      "title": "Dijous Bo 2025 - Uep IB3",
      "description": "Com ja és habitual en el Uep! Com anam?, pegarem un bot fins al Dijous Bo d’Inca per veure com estan els pagesos i ramaders de la zona, i també firmarem i farem cas a totes aquelles persones que passin per la nostra carpa i els hi entregarem el calendari del 2026. \n\n\"Uep! Com anam?\" és un programa de televisió d'IB3.\n\nhttp://ib3.org/uepcomanam\nhttp://facebook.com/uepcomanam",
      "thumbnail": "https://i.ytimg.com/vi/T7kh8gaoXxE/maxresdefault.jpg",
      "channelId": "UC3lLPAOb4cKzj6UN71cqeyQ",
      "channelTitle": "Uep! Com anam? IB3",
      "publishedAt": "2025-11-19T13:13:42Z",
      "categories": [
        "mitjans"
      ],
      "sourceChannelId": "UC3lLPAOb4cKzj6UN71cqeyQ",
      "duration": "PT6M35S",
      "durationSeconds": 395,
      "isShort": false,
      "viewCount": 131,
      "likeCount": 6,
      "commentCount": 1,
      "defaultAudioLanguage": "ca",
      "defaultLanguage": "ca",
      "tags": [
        "uep",
        "ib3",
        "tv",
        "illes balears",
        "mallorca",
        "pages",
        "rural",
        "camp",
        "eivissa",
        "formentera",
        "menorca",
        "animals",
        "vaca",
        "porc",
        "conill",
        "ovella",
        "xot",
        "pollet",
        "gallina",
        "gall"
      ]
    },
    {
      "id": "fALGhhvXxw8",
      "title": "Gató fet a Ariany - Uep IB3",
      "description": "Al rebost d’aquesta setmana, a Ariany, un forner ens prepara un gató mentre ens mostra diversos trucs i consells d’aquesta recepta, tant dolça com arrelada.\n\n\"Uep! Com anam?\" és un programa de televisió d'IB3.\n\nhttp://ib3.org/uepcomanam\nhttp://facebook.com/uepcomanam",
      "thumbnail": "https://i.ytimg.com/vi/fALGhhvXxw8/maxresdefault.jpg",
      "channelId": "UC3lLPAOb4cKzj6UN71cqeyQ",
      "channelTitle": "Uep! Com anam? IB3",
      "publishedAt": "2025-11-14T08:00:58Z",
      "categories": [
        "mitjans"
      ],
      "sourceChannelId": "UC3lLPAOb4cKzj6UN71cqeyQ",
      "duration": "PT10M42S",
      "durationSeconds": 642,
      "isShort": false,
      "viewCount": 238,
      "likeCount": 6,
      "commentCount": 1,
      "defaultAudioLanguage": "ca",
      "defaultLanguage": "ca",
      "tags": [
        "uep",
        "ib3",
        "tv",
        "illes balears",
        "mallorca",
        "pages",
        "rural",
        "camp",
        "eivissa",
        "formentera",
        "menorca",
        "animals",
        "vaca",
        "porc",
        "conill",
        "ovella",
        "xot",
        "pollet",
        "gallina",
        "gall"
      ]
    },
    {
      "id": "Uu8lvaNMyoU",
      "title": "Nou pagès a Sant Mateu d'Albarca - Uep IB3",
      "description": "A Sant Mateu d’Albarca, a Eivissa, coneixerem un amant dels animals i ens explicarà la seva trajectòria que l’ha duit fins a fora vila, on ha trobat, en el camp, un refugi i una nova manera de començar després de diverses experiències vitals.\n\"Uep! Com anam?\" és un programa de televisió d'IB3.\n\nhttp://ib3.org/uepcomanam\nhttp://facebook.com/uepcomanam",
      "thumbnail": "https://i.ytimg.com/vi/Uu8lvaNMyoU/maxresdefault.jpg",
      "channelId": "UC3lLPAOb4cKzj6UN71cqeyQ",
      "channelTitle": "Uep! Com anam? IB3",
      "publishedAt": "2025-11-14T08:00:45Z",
      "categories": [
        "mitjans"
      ],
      "sourceChannelId": "UC3lLPAOb4cKzj6UN71cqeyQ",
      "duration": "PT8M27S",
      "durationSeconds": 507,
      "isShort": false,
      "viewCount": 129,
      "likeCount": 3,
      "commentCount": 0,
      "defaultAudioLanguage": "ca",
      "defaultLanguage": "ca",
      "tags": [
        "uep",
        "ib3",
        "tv",
        "illes balears",
        "mallorca",
        "pages",
        "rural",
        "camp",
        "eivissa",
        "formentera",
        "menorca",
        "animals",
        "vaca",
        "porc",
        "conill",
        "ovella",
        "xot",
        "pollet",
        "gallina",
        "gall"
      ]
    },
    {
      "id": "2Qk1XuB_AOY",
      "title": "UEP! COMA ANAM? [731] - HORT D’HIVERN, EMPELTS A CALVIÀ, NOU PAGÈS A SANT MATEU I GATÓ A ARIANY",
      "description": "Com ja és habitual en el Uep! Com anam?, pegarem un bot fins al Dijous Bo d’Inca per veure com estan els pagesos i ramaders de la zona, i també firmarem i farem cas a totes aquelles persones que passin per la nostra carpa i els hi entregarem el calendari del 2026. A més, l’amo de Can Uep!, en Toni Ballador, serà a Algaida, per sembrar hortalisses per preparar l’hort d’hivern. El nostre jove pagès, en Lander, visitarà Can Ros, de Calvià, on farem un petit exercici de conscienciació amb la natura, observant els residus que sovint acaben dins les finques i descarregarem uns quants barrals d’oli de collita pròpia i visitant una antiga tafona que es troba en procés de restauració. A Sant Mateu d’Albarca, a Eivissa, coneixerem un amant dels animals i ens explicarà la seva trajectòria que l’ha duit fins a fora vila, on ha trobat, en el camp, un refugi i una nova manera de començar després de diverses experiències vitals. Al rebost d’aquesta setmana, a Ariany, un forner ens prepara un gató mentre ens mostra diversos trucs i consells d’aquesta recepta, tant dolça com arrelada. I com cada setmana, farem gloses i dites amb el nostre mestre de mestres, en Felip Munar i Munar.\n\n\"Uep! Com anam?\" és un programa de televisió d'IB3.\n\nhttp://ib3.org/uepcomanam\nhttp://facebook.com/uepcomanam",
      "thumbnail": "https://i.ytimg.com/vi/2Qk1XuB_AOY/maxresdefault.jpg",
      "channelId": "UC3lLPAOb4cKzj6UN71cqeyQ",
      "channelTitle": "Uep! Com anam? IB3",
      "publishedAt": "2025-11-14T08:00:04Z",
      "categories": [
        "mitjans"
      ],
      "sourceChannelId": "UC3lLPAOb4cKzj6UN71cqeyQ",
      "duration": "PT1H5M22S",
      "durationSeconds": 3922,
      "isShort": false,
      "viewCount": 546,
      "likeCount": 10,
      "commentCount": 0,
      "defaultAudioLanguage": "ca",
      "defaultLanguage": "ca",
      "tags": [
        "uep",
        "ib3",
        "tv",
        "illes balears",
        "mallorca",
        "pages",
        "rural",
        "camp",
        "eivissa",
        "formentera",
        "menorca",
        "animals",
        "vaca",
        "porc",
        "conill",
        "ovella",
        "xot",
        "pollet",
        "gallina",
        "gall"
      ]
    },
    {
      "id": "dqSVcz6Ht3s",
      "title": "Pilotes de calamar i sobrassada a Sa Calobra  - Uep IB3",
      "description": "Al rebost d’aquesta setmana, ens n'anem fins a Sa Calobra on, de la mà d’un xef i del seu ajudant de cuina, veurem com es fa aquesta recepta tradicional, però amb un toc renovat, com són les pilotes de calamar i sobrassada.\n\n\"Uep! Com anam?\" és un programa de televisió d'IB3.\n\nhttp://ib3.org/uepcomanam\nhttp://facebook.com/uepcomanam",
      "thumbnail": "https://i.ytimg.com/vi/dqSVcz6Ht3s/maxresdefault.jpg",
      "channelId": "UC3lLPAOb4cKzj6UN71cqeyQ",
      "channelTitle": "Uep! Com anam? IB3",
      "publishedAt": "2025-11-07T08:00:54Z",
      "categories": [
        "mitjans"
      ],
      "sourceChannelId": "UC3lLPAOb4cKzj6UN71cqeyQ",
      "duration": "PT13M57S",
      "durationSeconds": 837,
      "isShort": false,
      "viewCount": 314,
      "likeCount": 12,
      "commentCount": 0,
      "defaultAudioLanguage": "ca",
      "defaultLanguage": "ca",
      "tags": [
        "uep",
        "ib3",
        "tv",
        "illes balears",
        "mallorca",
        "pages",
        "rural",
        "camp",
        "eivissa",
        "formentera",
        "menorca",
        "animals",
        "vaca",
        "porc",
        "conill",
        "ovella",
        "xot",
        "pollet",
        "gallina",
        "gall"
      ]
    },
    {
      "id": "gFozV6PDakA",
      "title": "Cacauets de sa Pobla - Uep IB3",
      "description": "A Sa Pobla coneixerem a un jove pagès que collirà els cacauets i veurem com es duu a terme la neteja i el posterior assecat d’aquests.\n\n\"Uep! Com anam?\" és un programa de televisió d'IB3.\n\nhttp://ib3.org/uepcomanam\nhttp://facebook.com/uepcomanam",
      "thumbnail": "https://i.ytimg.com/vi/gFozV6PDakA/maxresdefault.jpg",
      "channelId": "UC3lLPAOb4cKzj6UN71cqeyQ",
      "channelTitle": "Uep! Com anam? IB3",
      "publishedAt": "2025-11-07T08:00:53Z",
      "categories": [
        "mitjans"
      ],
      "sourceChannelId": "UC3lLPAOb4cKzj6UN71cqeyQ",
      "duration": "PT9M39S",
      "durationSeconds": 579,
      "isShort": false,
      "viewCount": 111,
      "likeCount": 3,
      "commentCount": 0,
      "defaultAudioLanguage": "ca",
      "defaultLanguage": "ca",
      "tags": [
        "uep",
        "ib3",
        "tv",
        "illes balears",
        "mallorca",
        "pages",
        "rural",
        "camp",
        "eivissa",
        "formentera",
        "menorca",
        "animals",
        "vaca",
        "porc",
        "conill",
        "ovella",
        "xot",
        "pollet",
        "gallina",
        "gall"
      ]
    },
    {
      "id": "6in5D5vPqXs",
      "title": "UEP! COM ANAM? [730] - SEMBRAREM AL PLA DE NA TESA, COLLIREM A EIVISSA I CUINAREM A SA CALOBRA",
      "description": "Aquesta setmana, l’amo de Can Uep!, en Toni Ballador, visitarà una antiga vaqueria al Pla de Na Tesa. Començarem el dia donant menjar a les ovelles i llaurant la terra per preparar-la per a les hortalisses d’hivern que hi sembraran. Colliran fruits de temporada com són els codonys i les pomes i acabarem la jornada amb un berenar de frit. El nostre jove pagès, en Lander, anirà a Eivissa per gaudir d’una jornada a l’hort. D’arribada collirem albergínies i aprendrem a treure moniatos de terra. Continuarem collint alguns pebres, tant verds com vermells, i acabarem la jornada netejant i encaixonant la collita del dia per a la seva venda. A Sa Pobla coneixerem a un jove pagès que collirà els cacauets i veurem com es duu a terme la neteja i el posterior assecat d’aquests. Al rebost d’aquesta setmana, ens n'anem fins a Sa Calobra on, de la mà d’un xef i del seu ajudant de cuina, veurem com es fa aquesta recepta tradicional, però amb un toc renovat, com són les pilotes de calamar i sobrassada. I com cada setmana, farem gloses i dites amb el nostre mestre de mestres, en Felip Munar i Munar.\n\n\"Uep! Com anam?\" és un programa de televisió d'IB3.\n\nhttp://ib3.org/uepcomanam\nhttp://facebook.com/uepcomanam",
      "thumbnail": "https://i.ytimg.com/vi/6in5D5vPqXs/maxresdefault.jpg",
      "channelId": "UC3lLPAOb4cKzj6UN71cqeyQ",
      "channelTitle": "Uep! Com anam? IB3",
      "publishedAt": "2025-11-07T08:00:10Z",
      "categories": [
        "mitjans"
      ],
      "sourceChannelId": "UC3lLPAOb4cKzj6UN71cqeyQ",
      "duration": "PT1H13M49S",
      "durationSeconds": 4429,
      "isShort": false,
      "viewCount": 462,
      "likeCount": 5,
      "commentCount": 0,
      "defaultAudioLanguage": "ca",
      "defaultLanguage": "ca",
      "tags": [
        "uep",
        "ib3",
        "tv",
        "illes balears",
        "mallorca",
        "pages",
        "rural",
        "camp",
        "eivissa",
        "formentera",
        "menorca",
        "animals",
        "vaca",
        "porc",
        "conill",
        "ovella",
        "xot",
        "pollet",
        "gallina",
        "gall"
      ]
    },
    {
      "id": "zrJURngi7kc",
      "title": "Cogombres i pol·linització a Terracor - Uep IB3",
      "description": "A Manacor, compartirem una jornada de feina amb un pagès de professió. Collirem cogombres i descobrirem com es duu a terme la pol·linització dins els hivernacles.\n\n\"Uep! Com anam?\" és un programa de televisió d'IB3.\n\nhttp://ib3.org/uepcomanam\nhttp://facebook.com/uepcomanam",
      "thumbnail": "https://i.ytimg.com/vi/zrJURngi7kc/maxresdefault.jpg",
      "channelId": "UC3lLPAOb4cKzj6UN71cqeyQ",
      "channelTitle": "Uep! Com anam? IB3",
      "publishedAt": "2025-10-31T08:01:18Z",
      "categories": [
        "mitjans"
      ],
      "sourceChannelId": "UC3lLPAOb4cKzj6UN71cqeyQ",
      "duration": "PT8M43S",
      "durationSeconds": 523,
      "isShort": false,
      "viewCount": 83,
      "likeCount": 0,
      "commentCount": 0,
      "defaultAudioLanguage": "ca",
      "defaultLanguage": "ca",
      "tags": [
        "uep",
        "ib3",
        "tv",
        "illes balears",
        "mallorca",
        "pages",
        "rural",
        "camp",
        "eivissa",
        "formentera",
        "menorca",
        "animals",
        "vaca",
        "porc",
        "conill",
        "ovella",
        "xot",
        "pollet",
        "gallina",
        "gall"
      ]
    },
    {
      "id": "9_5DcKoCyAE",
      "title": "UEP! COM ANAM? [729] - COLLIREM OLIVES A SON MARCH, JORNADA ENTRE FRUITERS A BÚGER I CUINAREM RAOLES",
      "description": "Aquesta setmana, l’amo de Can Uep!, en Toni Ballador, serà Son March, a prop de Sa Pobla, on visitarem una finca amb una bona quantitat d'oliveres. Veurem un antic pou de prop de dos segles d’història situat sota la casa i arreplegarem algunes olives per elaborar-ne un parell de pots. Per clourem el dia visitarem l’escola de ximbomba, on interpretarem una cançó amb tots els membres del grup. El nostre jove pagès, en Lander, se’n va fins a Búger a conèixer un planterista de primer nivell amb qui gaudirem d’una jornada entre arbres fruiters. Començarem posant etiquetes a les oliveres, collint albercoquers i pruneres i descobrint quines són les varietats més sol•licitades d’arbres fruiters. Tot seguit, aprendrem com es fa un empelt d’ametller i analitzarem la principal problemàtica que tenen aquests arbres avui dia. A Manacor, compartirem una jornada de feina amb un pagès de professió. Collirem cogombres i descobrirem com es duu a terme la pol·linització dins els hivernacles. Al rebost d’aquesta setmana, des d’Algaida, ens posarem el davantal per preparar una recepta ben nostra: raoles de bleda i peixos de la terra. I com cada setmana, farem gloses i dites amb el nostre mestre de mestres, en Felip Munar i Munar.\n\n\"Uep! Com anam?\" és un programa de televisió d'IB3.\n\nhttp://ib3.org/uepcomanam\nhttp://facebook.com/uepcomanam",
      "thumbnail": "https://i.ytimg.com/vi/9_5DcKoCyAE/maxresdefault.jpg",
      "channelId": "UC3lLPAOb4cKzj6UN71cqeyQ",
      "channelTitle": "Uep! Com anam? IB3",
      "publishedAt": "2025-10-31T08:00:20Z",
      "categories": [
        "mitjans"
      ],
      "sourceChannelId": "UC3lLPAOb4cKzj6UN71cqeyQ",
      "duration": "PT1H18M13S",
      "durationSeconds": 4693,
      "isShort": false,
      "viewCount": 473,
      "likeCount": 6,
      "commentCount": 0,
      "defaultAudioLanguage": "ca",
      "defaultLanguage": "ca",
      "tags": [
        "uep",
        "ib3",
        "tv",
        "illes balears",
        "mallorca",
        "pages",
        "rural",
        "camp",
        "eivissa",
        "formentera",
        "menorca",
        "animals",
        "vaca",
        "porc",
        "conill",
        "ovella",
        "xot",
        "pollet",
        "gallina",
        "gall"
      ]
    },
    {
      "id": "3EMOJgZCZT0",
      "title": "Raoles de bledes i peixos de terra a Algaida - Uep IB3",
      "description": "Al rebost d’aquesta setmana, des d’Algaida, ens posarem el davantal per preparar una recepta ben nostrada: raoles de bleda i peixos de la terra.\n\n\"Uep! Com anam?\" és un programa de televisió d'IB3.\n\nhttp://ib3.org/uepcomanam\nhttp://facebook.com/uepcomanam",
      "thumbnail": "https://i.ytimg.com/vi/3EMOJgZCZT0/maxresdefault.jpg",
      "channelId": "UC3lLPAOb4cKzj6UN71cqeyQ",
      "channelTitle": "Uep! Com anam? IB3",
      "publishedAt": "2025-10-31T08:00:06Z",
      "categories": [
        "mitjans"
      ],
      "sourceChannelId": "UC3lLPAOb4cKzj6UN71cqeyQ",
      "duration": "PT10M31S",
      "durationSeconds": 631,
      "isShort": false,
      "viewCount": 243,
      "likeCount": 10,
      "commentCount": 1,
      "defaultAudioLanguage": "ca",
      "defaultLanguage": "ca",
      "tags": [
        "uep",
        "ib3",
        "tv",
        "illes balears",
        "mallorca",
        "pages",
        "rural",
        "camp",
        "eivissa",
        "formentera",
        "menorca",
        "animals",
        "vaca",
        "porc",
        "conill",
        "ovella",
        "xot",
        "pollet",
        "gallina",
        "gall"
      ]
    },
    {
      "id": "tB3uV_OJdG4",
      "title": "Pebres, peres i alvocats a Son Bacs d'Ariany - Uep IB3",
      "description": "Anirem fins a la finca de Son Bacs, a Ariany, per passar un temps amb l’amo de la finca. Aprofitarem per collir pebres, peres i alguns alvocats al mateix temps que compartim coneixements.\n\n\"Uep! Com anam?\" és un programa de televisió d'IB3.\n\nhttp://ib3.org/uepcomanam\nhttp://facebook.com/uepcomanam",
      "thumbnail": "https://i.ytimg.com/vi/tB3uV_OJdG4/maxresdefault.jpg",
      "channelId": "UC3lLPAOb4cKzj6UN71cqeyQ",
      "channelTitle": "Uep! Com anam? IB3",
      "publishedAt": "2025-10-24T07:00:50Z",
      "categories": [
        "mitjans"
      ],
      "sourceChannelId": "UC3lLPAOb4cKzj6UN71cqeyQ",
      "duration": "PT9M42S",
      "durationSeconds": 582,
      "isShort": false,
      "viewCount": 124,
      "likeCount": 3,
      "commentCount": 1,
      "defaultAudioLanguage": "ca",
      "defaultLanguage": "ca",
      "tags": [
        "uep",
        "ib3",
        "tv",
        "illes balears",
        "mallorca",
        "pages",
        "rural",
        "camp",
        "eivissa",
        "formentera",
        "menorca",
        "animals",
        "vaca",
        "porc",
        "conill",
        "ovella",
        "xot",
        "pollet",
        "gallina",
        "gall"
      ]
    },
    {
      "id": "UAXPlvBk2N0",
      "title": "Empotat d'albergínies amb padrina i neta de s'Horta - Uep IB3",
      "description": "Al rebost d’aquesta setmana, anirem fins a s’Horta a conèixer una jove que els darrers mesos s’ha fet popular a les xarxes socials i que ens farà un empotat d’albergínies amb l’ajuda final de la seva padrina.  \n\n\"Uep! Com anam?\" és un programa de televisió d'IB3.\n\nhttp://ib3.org/uepcomanam\nhttp://facebook.com/uepcomanam",
      "thumbnail": "https://i.ytimg.com/vi/UAXPlvBk2N0/maxresdefault.jpg",
      "channelId": "UC3lLPAOb4cKzj6UN71cqeyQ",
      "channelTitle": "Uep! Com anam? IB3",
      "publishedAt": "2025-10-24T07:00:33Z",
      "categories": [
        "mitjans"
      ],
      "sourceChannelId": "UC3lLPAOb4cKzj6UN71cqeyQ",
      "duration": "PT12M58S",
      "durationSeconds": 778,
      "isShort": false,
      "viewCount": 215,
      "likeCount": 8,
      "commentCount": 1,
      "defaultAudioLanguage": "ca",
      "defaultLanguage": "ca",
      "tags": [
        "uep",
        "ib3",
        "tv",
        "illes balears",
        "mallorca",
        "pages",
        "rural",
        "camp",
        "eivissa",
        "formentera",
        "menorca",
        "animals",
        "vaca",
        "porc",
        "conill",
        "ovella",
        "xot",
        "pollet",
        "gallina",
        "gall"
      ]
    },
    {
      "id": "DkiLhvf_cTM",
      "title": "UEP! COM ANAM? [728] - LA MARINA DE LLUCMAJOR, FUTUR ENGINYER AGRÒNOM I EMPOTAT D’ALBERGÍNIES",
      "description": "Aquesta setmana, l’amo de Can Uep!, en Toni Ballador, visitarà la finca de Can Garraseca, a Llucmajor, per conèixer com era i com és la marina de Llucmajor. Començarem veient uns clapers, unes construccions típiques que formen part del paisatge mallorquí. Després, netejarem l’entrada d’aigua d’una cisterna i tallarem dos rams de mata, que farem servir com a ambientador natural. Més tard, arreglarem una barraca de roter utilitzant l'antiga i popular tècnica de la pedra seca. I per acabar, berenarem amb els senyors de la possessió, gaudint d’una estona de conversa, bones històries i germanor. El nostre jove pagès, en Lander, se’n va fins a Inca per conèixer a un futur enginyer agrònom. Començarem el dia munyint ovelles i donant-los menjar als sestadors. Després, donarem menjar als porcs i acabarem les feines a la finca exsecallant garrovers joves, una feina que ajuda els arbres a créixer forts i sans. Per acabar la jornada, anirem fins a la UIB per assistir a una de les classes del grau en Enginyeria Agronòmica, on veurem com funciona el curs i coneixerem de prop els alumnes i el professor. Serà una experiència completa, entre el camp i l’aula, per entendre millor com es forma la nova generació de professionals del sector agrari. Anirem fins a la finca de Son Bacs, a Ariany, per passar un temps amb l’amo de la finca. Aprofitarem per collir pebres, peres i alguns alvocats al mateix temps que compartim coneixements. Al rebost d’aquesta setmana, anirem fins a s’Horta a conèixer una jove que els darrers mesos s’ha fet popular a les xarxes socials i que ens farà un empotat d’albergínies amb l’ajuda final de la seva padrina. I com cada setmana, farem gloses i dites amb el nostre mestre de mestres, en Felip Munar i Munar.\n\n\"Uep! Com anam?\" és un programa de televisió d'IB3.\n\nhttp://ib3.org/uepcomanam\nhttp://facebook.com/uepcomanam",
      "thumbnail": "https://i.ytimg.com/vi/DkiLhvf_cTM/maxresdefault.jpg",
      "channelId": "UC3lLPAOb4cKzj6UN71cqeyQ",
      "channelTitle": "Uep! Com anam? IB3",
      "publishedAt": "2025-10-24T07:00:13Z",
      "categories": [
        "mitjans"
      ],
      "sourceChannelId": "UC3lLPAOb4cKzj6UN71cqeyQ",
      "duration": "PT1H19M55S",
      "durationSeconds": 4795,
      "isShort": false,
      "viewCount": 499,
      "likeCount": 6,
      "commentCount": 0,
      "defaultAudioLanguage": "ca",
      "defaultLanguage": "ca",
      "tags": [
        "uep",
        "ib3",
        "tv",
        "illes balears",
        "mallorca",
        "pages",
        "rural",
        "camp",
        "eivissa",
        "formentera",
        "menorca",
        "animals",
        "vaca",
        "porc",
        "conill",
        "ovella",
        "xot",
        "pollet",
        "gallina",
        "gall"
      ]
    },
    {
      "id": "eHj7ZIyRsLA",
      "title": "Catalina Fuster futura campiona de trot  - Uep IB3",
      "description": "Anirem fins a Artà a conèixer a la representant nacional al Campionat Europeu d’Aprenents. Veurem com és el procés de preparació del cavall per entrenar i acabarem fent un passeig per entendre més a fons la vida d’aquesta futura campiona.\n\n\"Uep! Com anam?\" és un programa de televisió d'IB3.\n\nhttp://ib3.org/uepcomanam\nhttp://facebook.com/uepcomanam",
      "thumbnail": "https://i.ytimg.com/vi/eHj7ZIyRsLA/maxresdefault.jpg",
      "channelId": "UC3lLPAOb4cKzj6UN71cqeyQ",
      "channelTitle": "Uep! Com anam? IB3",
      "publishedAt": "2025-10-17T07:00:41Z",
      "categories": [
        "mitjans"
      ],
      "sourceChannelId": "UC3lLPAOb4cKzj6UN71cqeyQ",
      "duration": "PT10M18S",
      "durationSeconds": 618,
      "isShort": false,
      "viewCount": 263,
      "likeCount": 3,
      "commentCount": 0,
      "defaultAudioLanguage": "ca",
      "defaultLanguage": "ca",
      "tags": [
        "uep",
        "ib3",
        "tv",
        "illes balears",
        "mallorca",
        "pages",
        "rural",
        "camp",
        "eivissa",
        "formentera",
        "menorca",
        "animals",
        "vaca",
        "porc",
        "conill",
        "ovella",
        "xot",
        "pollet",
        "gallina",
        "gall"
      ]
    },
    {
      "id": "7FVxlT9YfdE",
      "title": "Bunyols de les Verges a Alcúdia - Uep IB3",
      "description": "Al rebost d’aquesta setmana, anirem fins a Alcúdia per conèixer a una mestra bunyolera, la recepta autèntica dels bunyols i com els fa.\n\n\"Uep! Com anam?\" és un programa de televisió d'IB3.\n\nhttp://ib3.org/uepcomanam\nhttp://facebook.com/uepcomanam",
      "thumbnail": "https://i.ytimg.com/vi/7FVxlT9YfdE/maxresdefault.jpg",
      "channelId": "UC3lLPAOb4cKzj6UN71cqeyQ",
      "channelTitle": "Uep! Com anam? IB3",
      "publishedAt": "2025-10-17T07:00:12Z",
      "categories": [
        "mitjans"
      ],
      "sourceChannelId": "UC3lLPAOb4cKzj6UN71cqeyQ",
      "duration": "PT8M32S",
      "durationSeconds": 512,
      "isShort": false,
      "viewCount": 692,
      "likeCount": 18,
      "commentCount": 1,
      "defaultAudioLanguage": "ca",
      "defaultLanguage": "ca",
      "tags": [
        "uep",
        "ib3",
        "tv",
        "illes balears",
        "mallorca",
        "pages",
        "rural",
        "camp",
        "eivissa",
        "formentera",
        "menorca",
        "animals",
        "vaca",
        "porc",
        "conill",
        "ovella",
        "xot",
        "pollet",
        "gallina",
        "gall"
      ]
    }
  ]
}